FPE/FPE.py
FPE/Format.py
FPE/Mode.py
FPE/__init__.py
FPE/ff1.cp39-win_amd64.pyd
FPE/ff3.cp39-win_amd64.pyd
FPE/format_translator.py
FPE/formatter.py
FPE/fpe_csv.py
FPE/mode_selector.py
FPE-0.1.2.dist-info/LICENSE.txt
FPE-0.1.2.dist-info/METADATA
FPE-0.1.2.dist-info/WHEEL
FPE-0.1.2.dist-info/top_level.txt
FPE-0.1.2.dist-info/RECORD
