Metadata-Version: 2.1
Name: FPE
Version: 0.1.2
Summary: Format Preserving Encryption with FF1 and FF3-1
Home-page: UNKNOWN
Author: Gustav Grønvold
Author-email: ggroenvold@live.dk
License: MIT
Platform: UNKNOWN
Classifier: License :: OSI Approved :: MIT License
Classifier: Intended Audience :: Education
Classifier: Intended Audience :: Science/Research
Classifier: Topic :: Scientific/Engineering
Classifier: Topic :: Scientific/Engineering :: Mathematics
Classifier: Natural Language :: English
Classifier: Operating System :: OS Independent
Classifier: Programming Language :: C
Classifier: Programming Language :: Cython
Classifier: Programming Language :: Python
Classifier: Programming Language :: Python :: 3
Classifier: Programming Language :: Python :: 3.7
Classifier: Programming Language :: Python :: 3.8
Classifier: Programming Language :: Python :: 3.9
Classifier: Programming Language :: Python :: 3.10
Classifier: Programming Language :: Python :: Implementation :: CPython
Requires-Python: >=3.7
License-File: LICENSE.txt
Requires-Dist: Cython (>=0.29.24)
Requires-Dist: numpy (>=1.21.4)
Requires-Dist: pycryptodome (>=3.11.0)
